AUTHORS
CHANGES
ChangeLog
README.md
requirements.txt
setup.cfg
setup.py
tests/__init__.py
tests/a.yml
tests/b.yml
tests/c.yml
tests/test_load.py
tests/eg_folder/__init__.py
tests/eg_folder/c.yml
yamlplus/__init__.py
yamlplus.egg-info/PKG-INFO
yamlplus.egg-info/SOURCES.txt
yamlplus.egg-info/dependency_links.txt
yamlplus.egg-info/not-zip-safe
yamlplus.egg-info/pbr.json
yamlplus.egg-info/requires.txt
yamlplus.egg-info/top_level.txt