Metadata-Version: 1.2
Name: yamlplus
Version: 1.1.0.dev2
Summary: yaml puls
Home-page: https://github.com/Mengjianhua-c/pyyaml-plus
Author: mengjianhua
Author-email: 1711621009@qq.com
License: MIT
Keywords: pyyaml, pyyaml plus
Platform: UNKNOWN
Classifier: Development Status :: 4 - Beta
Classifier: Environment :: Console
Classifier: Intended Audience :: Developers
Classifier: Operating System :: POSIX
Classifier: Programming Language :: Python :: 3
Classifier: Topic :: Software Development :: Libraries :: Python Modules
Classifier: Topic :: Software Development :: Testing
Requires-Python: >=3.6
